hello_jackie_practice/__init__.py
hello_jackie_practice/main.py
hello_jackie_practice-0.1.1.dist-info/METADATA
hello_jackie_practice-0.1.1.dist-info/WHEEL
hello_jackie_practice-0.1.1.dist-info/top_level.txt
hello_jackie_practice-0.1.1.dist-info/RECORD
