Metadata-Version: 2.1
Name: hello-jackie-practice
Version: 0.1.1
Summary: my first package
